biblyser/__init__.py
biblyser/bib.py
biblyser/bibcollection.py
biblyser/name.py
biblyser/organisation.py
biblyser-0.0.1.dist-info/LICENSE
biblyser-0.0.1.dist-info/METADATA
biblyser-0.0.1.dist-info/WHEEL
biblyser-0.0.1.dist-info/top_level.txt
biblyser-0.0.1.dist-info/RECORD
