Metadata-Version: 2.1
Name: biblyser
Version: 0.0.1
Summary: A bibliometric workflow for evaluating the bib metrics of an individual or group of people
Home-page: https://github.com/GEUS-Glaciology-and-Climate/Biblyser
Author: Penelope How
Author-email: pho@geus.dk
License: UNKNOWN
Project-URL: Bug Tracker, https://github.com/GEUS-Glaciology-and-Climate/Biblyser/issues
Keywords: publications citations academia science bibliometrics
Platform: UNKNOWN
Classifier: Programming Language :: Python :: 3
Classifier: License :: OSI Approved :: MIT License
Classifier: Development Status :: 4 - Beta
Classifier: Intended Audience :: Science/Research
Classifier: Natural Language :: English
Classifier: Topic :: Scientific/Engineering
Classifier: Operating System :: OS Independent
Requires-Python: >=3.7
Requires-Dist: gender-guesser
Requires-Dist: habanero
Requires-Dist: numpy
Requires-Dist: pandas
Requires-Dist: pybliometrics
Requires-Dist: scholarly
